puhdistusalue/__init__.py
puhdistusalue/__main__.py
puhdistusalue/cli.py
puhdistusalue/puhdistusalue.py
tests/__init__.py
tests/context.py
tests/test_cli.py
tests/test_puhdistusalue.py
puhdistusalue-2022.6.29.dist-info/LICENSE
puhdistusalue-2022.6.29.dist-info/METADATA
puhdistusalue-2022.6.29.dist-info/WHEEL
puhdistusalue-2022.6.29.dist-info/entry_points.txt
puhdistusalue-2022.6.29.dist-info/top_level.txt
puhdistusalue-2022.6.29.dist-info/RECORD
