Metadata-Version: 2.1
Name: puhdistusalue
Version: 2022.6.29
Summary: Puhdistusalue (Finnish for clean area here meaning purge range) - Purge monotonically named files in folders keeping range endpoints.
Home-page: https://github.com/sthagen/puhdistusalue
Author: Stefan Hagen
Author-email: stefan@hagen.link
Maintainer: Stefan Hagen
Maintainer-email: stefan@hagen.link
Project-URL: Bug Tracker, https://github.com/sthagen/puhdistusalue/issues
Project-URL: Documentation, https://sthagen.github.io/puhdistusalue
Project-URL: Source Code, https://github.com/sthagen/puhdistusalue
Keywords: compression,developer-tools,file-processing
Classifier: Development Status :: 4 - Beta
Classifier: Intended Audience :: Developers
Classifier: License :: OSI Approved :: MIT License
Classifier: Programming Language :: Python :: 3.10
Classifier: Programming Language :: Python :: 3.8
Classifier: Programming Language :: Python :: 3.9
Classifier: Topic :: Software Development :: Build Tools
Requires-Python: >=3.8
License-File: LICENSE
Requires-Dist: puristaa (>=2022.6.27)
Provides-Extra: dev
Requires-Dist: black ; extra == 'dev'
Requires-Dist: coverage ; extra == 'dev'
Requires-Dist: flake8 ; extra == 'dev'
Requires-Dist: mypy ; extra == 'dev'
Requires-Dist: pytest ; extra == 'dev'
Requires-Dist: pytest-cov ; extra == 'dev'
Requires-Dist: pytest-flake8 ; extra == 'dev'
